meraki/__init__.py
meraki/common.py
meraki/config.py
meraki/exceptions.py
meraki/response_handler.py
meraki/rest_session.py
meraki/aio/__init__.py
meraki/aio/rest_session.py
meraki/aio/api/__init__.py
meraki/aio/api/administered.py
meraki/aio/api/appliance.py
meraki/aio/api/camera.py
meraki/aio/api/campusGateway.py
meraki/aio/api/cellularGateway.py
meraki/aio/api/devices.py
meraki/aio/api/insight.py
meraki/aio/api/licensing.py
meraki/aio/api/nac.py
meraki/aio/api/networks.py
meraki/aio/api/organizations.py
meraki/aio/api/sensor.py
meraki/aio/api/sm.py
meraki/aio/api/spaces.py
meraki/aio/api/switch.py
meraki/aio/api/wireless.py
meraki/aio/api/wirelessController.py
meraki/api/__init__.py
meraki/api/administered.py
meraki/api/appliance.py
meraki/api/camera.py
meraki/api/campusGateway.py
meraki/api/cellularGateway.py
meraki/api/devices.py
meraki/api/insight.py
meraki/api/licensing.py
meraki/api/nac.py
meraki/api/networks.py
meraki/api/organizations.py
meraki/api/sensor.py
meraki/api/sm.py
meraki/api/spaces.py
meraki/api/switch.py
meraki/api/wireless.py
meraki/api/wirelessController.py
meraki/api/batch/__init__.py
meraki/api/batch/administered.py
meraki/api/batch/appliance.py
meraki/api/batch/camera.py
meraki/api/batch/campusGateway.py
meraki/api/batch/cellularGateway.py
meraki/api/batch/devices.py
meraki/api/batch/insight.py
meraki/api/batch/licensing.py
meraki/api/batch/nac.py
meraki/api/batch/networks.py
meraki/api/batch/organizations.py
meraki/api/batch/sensor.py
meraki/api/batch/sm.py
meraki/api/batch/spaces.py
meraki/api/batch/switch.py
meraki/api/batch/wireless.py
meraki/api/batch/wirelessController.py
meraki-2.1.0.dist-info/licenses/LICENSE
meraki-2.1.0.dist-info/METADATA
meraki-2.1.0.dist-info/WHEEL
meraki-2.1.0.dist-info/top_level.txt
meraki-2.1.0.dist-info/RECORD
